MANIFEST.in
NEWS.txt
README.rst
setup.py
src/deskapi/__init__.py
src/deskapi/models.py
src/deskapi/six.py
src/deskapi.egg-info/PKG-INFO
src/deskapi.egg-info/SOURCES.txt
src/deskapi.egg-info/dependency_links.txt
src/deskapi.egg-info/not-zip-safe
src/deskapi.egg-info/requires.txt
src/deskapi.egg-info/top_level.txt
src/deskapi/tests/__init__.py
src/deskapi/tests/test_articles_api.py
src/deskapi/tests/test_session.py
src/deskapi/tests/test_topics_api.py
src/deskapi/tests/util.py