Metadata-Version: 1.0
Name: deskapi
Version: 0.1
Summary: UNKNOWN
Home-page: https://github.com/eventbrite/deskapi
Author: Nathan Yergler
Author-email: nathan@eventbrite.com
License: BSD
Platform: UNKNOWN
Classifier: License :: OSI Approved :: BSD License
